MANIFEST.in
README.rst
setup.py
bin/mjail
mjail/__init__.py
mjail/cd.py
mjail/cmd_helpers.py
mjail/commands.py
mjail/get_jail_conf.py
mjail/jails_network.py
mjail/local_unbound_enabled.py
mjail/pf_conf_split.py
mjail/services.py
mjail/settings.py
mjail/sshd_conf.py
mjail.egg-info/PKG-INFO
mjail.egg-info/SOURCES.txt
mjail.egg-info/dependency_links.txt
mjail.egg-info/requires.txt
mjail.egg-info/top_level.txt