Metadata-Version: 1.1
Name: mjail
Version: 0.1.1
Summary: Minimalist command line tool to manage FreeBSD jails
Home-page: https://github.com/leforestier/mjail
Author: Benjamin Le Forestier
Author-email: benjamin@leforestier.org
License: UNKNOWN
Keywords: jail,freebsd,jail.conf
Platform: UNKNOWN
Classifier: Intended Audience :: System Administrators
Classifier: Intended Audience :: Developers
Classifier: License :: OSI Approved :: BSD License
Classifier: Programming Language :: Python
Classifier: Programming Language :: Python :: 3
Classifier: Programming Language :: Python :: 3.5
Classifier: Programming Language :: Python :: 3.6
Classifier: Operating System :: POSIX :: BSD :: FreeBSD
Classifier: Topic :: System :: Operating System
Classifier: Topic :: System :: Systems Administration
